Workbook

Sheet Resumo Executivo
B2: ANÁLISE COMPARATIVA - 3 OPERAÇÕES FINIMP
B3: Custo financeiro puro (sem spread cambial). Foco: BB Tóquio × Santander Luxemburgo.
B5: Análise sem spread cambial - depende da oscilação do dólar no momento da operação. A comparação válida é BB Tóquio × Santander Luxemburgo (FINIMP puros). Itaú aparece como referência (estrutura híbrida com NDF altera comparabilidade).
B8: Componente | C8: BB Tóquio (R$) | D8: Itaú (ref.) | E8: Santander Lux (R$) | F8: Comentário
B9: Juros nominais brutos | C9: ='Cálculo BB'!E23 -> 29395 | D9: ='Cálculo Itaú'!E25 -> 24452 | E9: ='Cálculo Santander'!E25 -> 30400 | F9: BB: 5,88% | Itaú: 4,89% | Santander: 6,08%
B10: IRRF gross-up sobre juros | C10: ='Cálculo BB'!E24 -> 5187.3529 | D10: ='Cálculo Itaú'!E26 -> 8150.6667 | E10: ='Cálculo Santander'!E26 -> 10133.333 | F10: BB: 15% Tóquio | Itaú: 25% Nassau | Santander: 25% Lux
B11: Comissão garantia (SBLC/CPG) | C11: 0 | D11: ='Cálculo Itaú'!E27 -> 3874.5 | E11: ='Cálculo Santander'!E27 -> 2000 | F11: Itaú: SBLC 0,77% | Santander: CPG 0,40%
B12: IOF câmbio (entrada + saídas) | C12: ='Cálculo BB'!E25 -> 7731.4129 | D12: ='Cálculo Itaú'!E28 -> 7738.6132 | E12: ='Cálculo Santander'!E28 -> 7754.0267 | F12: 0,38% sobre conversões cambiais
B13: (+) Receita Financeira CDB cativo (líquida de IRRF 22,5%) | C13: =-(1000000*0.3*0.1475*180/360)*(1-0.225) -> -17146.875 | D13: =-(1000000*0.3*0.1475*180/360)*(1-0.225) -> -17146.875 | E13: =-(1000000*0.3*0.1475*180/360)*(1-0.225) -> -17146.875 | F13: CDB rende 100% do CDI - reduz custo líquido
B14: Custos cartoriais e fees fixos | C14: ='Cálculo BB'!E27 -> 1500 | D14: ='Cálculo Itaú'!E30 -> 1500 | E14: ='Cálculo Santander'!E30 -> 2500 | F14: Santander tem ROF + CADEMP
B15: CUSTO TOTAL DA OPERAÇÃO (R$) | C15: =SUM(C9:C14) -> 26666.891 | D15: =SUM(D9:D14) -> 28568.905 | E15: =SUM(E9:E14) -> 35640.485
B17: Custo total como % do principal (180 dias) | C17: =C15/1000000 -> 0.026666891 | D17: =D15/1000000 -> 0.028568905 | E17: =E15/1000000 -> 0.035640485
B18: Custo equivalente linear a.a. | C18: =C17*360/180 -> 0.053333782 | D18: =D17*360/180 -> 0.05713781 | E18: =E17*360/180 -> 0.07128097 | F18: Multiplicação direta por 360/180 (proporcional)
B19: CET equivalente a.a. (composto) | C19: =(1+C17)^(360/180)-1 -> 0.054044905 | D19: =(1+D17)^(360/180)-1 -> 0.057953992 | E19: =(1+E17)^(360/180)-1 -> 0.072551214 | F19: Capitalização composta - é maior que o linear
B22: COMPARAÇÃO DIRETA: BB TÓQUIO × SANTANDER LUXEMBURGO
B23: Componente | C23: BB Tóquio | D23: Santander Lux | E23: Δ (Sant - BB) | F23: Comentário
B24: Juros nominais brutos | C24: =C9 -> 29395 | D24: =E9 -> 30400 | E24: =E9-C9 -> 1005 | F24: BB: 5,88% | Itaú: 4,89% | Santander: 6,08%
B25: IRRF gross-up sobre juros | C25: =C10 -> 5187.3529 | D25: =E10 -> 10133.333 | E25: =E10-C10 -> 4945.9804 | F25: BB: 15% Tóquio | Itaú: 25% Nassau | Santander: 25% Lux
B26: Comissão garantia (SBLC/CPG) | C26: =C11 -> 0 | D26: =E11 -> 2000 | E26: =E11-C11 -> 2000 | F26: Itaú: SBLC 0,77% | Santander: CPG 0,40%
B27: IOF câmbio (entrada + saídas) | C27: =C12 -> 7731.4129 | D27: =E12 -> 7754.0267 | E27: =E12-C12 -> 22.613725 | F27: 0,38% sobre conversões cambiais
B28: (+) Receita Financeira CDB cativo (líquida de IRRF 22,5%) | C28: =-(1000000*0.3*0.1475*180/360)*(1-0.225) -> -17146.875 | D28: =-(1000000*0.3*0.1475*180/360)*(1-0.225) -> -17146.875 | E28: =-(1000000*0.3*0.1475*180/360)*(1-0.225) -> -17146.875 | F28: CDB rende 100% do CDI - reduz custo líquido
B29: Custos cartoriais e fees fixos | C29: =C14 -> 1500 | D29: =E14 -> 2500 | E29: =E14-C14 -> 1000 | F29: Santander tem ROF + CADEMP
B30: CUSTO TOTAL | C30: =C15 -> 26666.891 | D30: =E15 -> 35640.485 | E30: =E15-C15 -> 8973.5941

Sheet Visão DRE
B2: VISÃO DRE - SEPARAÇÃO RECEITA × DESPESA FINANCEIRA
B3: Visão contábil: a receita do CDB cativo é separada da despesa do FINIMP. O CDB rende 100% do CDI (não gera custo de oportunidade líquido), apenas movimenta linhas distintas da DRE: Receita Financeira (rendimento CDB) vs. Despesa Financeira (custos do FINIMP).
B6: PREMISSAS AUXILIARES
B7: Valor da operação (R$) | C7: 1000000
B8: Prazo (dias) | C8: 180
B9: % do principal em CDB cativo | C9: 0.3
B10: Taxa CDI a.a. | C10: 0.1475
B11: % do CDI rendido pelo CDB | C11: 1
B12: Base (dias/ano) | C12: 360
B13: IRRF sobre aplicação CDB (180d → 22,5%) | C13: 0.225
B16: DRE SIMPLIFICADA DA OPERAÇÃO
B17: Linha | C17: BB Tóquio | D17: Itaú (ref.) | E17: Santander Lux | F17: Comentário
B18: (+) RECEITA FINANCEIRA
B19: Rendimento bruto do CDB cativo (CDI a.a. × prazo / base) | C19: =C7*C9*C10*C11*C8/C12 -> 22125 | D19: =C7*C9*C10*C11*C8/C12 -> 22125 | E19: =C7*C9*C10*C11*C8/C12 -> 22125 | F19: R$ 300k × 14,75% × 180/360
B20: (-) IRRF sobre rendimento da aplicação (22,5% para 180d) | C20: =-C19*C13 -> -4978.125 | D20: =-D19*C13 -> -4978.125 | E20: =-E19*C13 -> -4978.125 | F20: Tabela regressiva IRRF aplicações financeiras
B21: (=) RECEITA FINANCEIRA LÍQUIDA | C21: =C19+C20 -> 17146.875 | D21: =D19+D20 -> 17146.875 | E21: =E19+E20 -> 17146.875
B23: (-) DESPESA FINANCEIRA
B24: Juros nominais (FINIMP) | C24: =-'Cálculo BB'!E23 -> -29395 | D24: =-'Cálculo Itaú'!E25 -> -24452 | E24: =-'Cálculo Santander'!E25 -> -30400 | F24: Saldo × taxa × prazo / 360
B25: IRRF gross-up sobre juros remetidos | C25: =-'Cálculo BB'!E24 -> -5187.3529 | D25: =-'Cálculo Itaú'!E26 -> -8150.6667 | E25: =-'Cálculo Santander'!E26 -> -10133.333 | F25: BB: 15% (Tóquio) | Itaú: 25% (Nassau) | Santander: 25% (Lux)
B26: Comissão de garantia (SBLC/CPG) | C26: 0 | D26: =-'Cálculo Itaú'!E27 -> -3874.5 | E26: =-'Cálculo Santander'!E27 -> -2000 | F26: Itaú: SBLC 0,77% | Santander: CPG 0,40%
B27: IOF câmbio (entrada + saída) | C27: =-'Cálculo BB'!E25 -> -7731.4129 | D27: =-'Cálculo Itaú'!E28 -> -7738.6132 | E27: =-'Cálculo Santander'!E28 -> -7754.0267 | F27: 0,38% sobre conversões
B28: Tarifas e fees fixos | C28: =-'Cálculo BB'!E27 -> -1500 | D28: =-'Cálculo Itaú'!E30 -> -1500 | E28: =-'Cálculo Santander'!E30 -> -2500 | F28: Cartórios, ROF, CADEMP
B29: (=) DESPESA FINANCEIRA TOTAL | C29: =SUM(C24:C28) -> -43813.766 | D29: =SUM(D24:D28) -> -45715.78 | E29: =SUM(E24:E28) -> -52787.36
B31: (=) RESULTADO FINANCEIRO LÍQUIDO | C31: =C21+C29 -> -26666.891 | D31: =D21+D29 -> -28568.905 | E31: =E21+E29 -> -35640.485
B33: Resultado financeiro como % do principal (180d) | C33: =C31/C7 -> -0.026666891 | D33: =D31/C7 -> -0.028568905 | E33: =E31/C7 -> -0.035640485
B34: Custo financeiro líquido equivalente a.a. (linear) | C34: =C33*C12/C8 -> -0.053333782 | D34: =D33*C12/C8 -> -0.05713781 | E34: =E33*C12/C8 -> -0.07128097
B37: COMPARAÇÃO DIRETA: BB × SANTANDER (Resultado Financeiro Líquido)
B38: Resultado financeiro líquido (R$, 180 dias) | C38: =C31 -> -26666.891 | D38: Δ (Sant - BB) | E38: =E31 -> -35640.485 | F38: =C38-E38 -> 8973.5941

Sheet Notas Metodológicas
B2: NOTAS METODOLÓGICAS
B4: 1. ESCOPO E LIMITAÇÕES
B5: • A análise comparativa parte de uma operação NOMINAL de R$ 1.000.000, ainda que os contratos originais tenham sido firmados em CNY (BB) e USD (Itaú). Para fins de comparação, assumimos que ambos pagariam principal em moeda estrangeira equivalente a R$ 1MM na data do desembolso.
B6: • A análise utiliza os dados REAIS dos dois contratos FINIMP. O contrato Itaú é com a FILIAL NASSAU (Bahamas), entidade no exterior considerada paraíso fiscal pela Receita Federal (IN RFB 1.037/2010), o que justifica a alíquota de IRRF de 25% (vs. 15% do BB Tóquio).
B8: 2. METODOLOGIA DE CÁLCULO DO CET
B9: O Custo Efetivo Total (CET) é composto pela soma de:
B10: (a) Juros nominais sobre o saldo devedor — base 360 dias, calculado pro rata diária
B11: (b) Tributos federais — IRRF sobre juros remetidos ao exterior (apenas BB Tóquio) e IOF câmbio
B12: (c) Custos cambiais — spread bid/ask aplicado nas conversões R$↔ME (entrada e saídas)
B13: (d) Custo de oportunidade — apenas Itaú (CDB cativo dado em garantia rende menos que aplicação livre)
B14: (e) Fees fixos — cartório, registro, taxa de abertura, etc.
B16: 3. PARTICULARIDADES TRIBUTÁRIAS DO BB TÓQUIO
... B40: • Alíquota efetiva de IOF câmbio aplicável (pode haver alíquotas reduzidas para FINIMP em alguns casos)

Sheet Cálculo BB
B2: CÁLCULO DETALHADO - FINIMP BB TÓQUIO (180 dias bullet, sem spread cambial)
B3: Análise de custo financeiro puro (juros + IRRF + IOF + CDB cativo + fees). Spread cambial REMOVIDO da análise pois depende da oscilação do dólar no momento da operação.
B6: PREMISSAS DA OPERAÇÃO
B7: Valor da operação (R$) | C7: 1000000 | D7: Operação base
B8: Prazo (dias) | C8: 180 | D8: Cenário ajustado: 180 dias
B9: Taxa de juros nominal a.a. | C9: 0.05879 | D9: Cláusula Quarta - 5,879% a.a.
B10: Base de cálculo (dias/ano) | C10: 360 | D10: Cláusula Quarta - ano de 360 dias
B11: Estrutura | C11: Bullet único | D11: Cenário ajustado
B12: IRRF sobre juros remetidos a Tóquio | C12: 0.15 | D12: Acordo Brasil-Japão de bitributação
B13: IOF câmbio (cada remessa) | C13: 0.0038 | D13: Alíquota geral 0,38%
B14: Cash Collateral (CDB cativo) - % do principal | C14: 0.3 | D14: Premissa: 30% (informado pelo usuário)
B15: Taxa CDI (custo de oportunidade) | C15: 0.1475 | D15: Premissa - SELIC/CDI atual
B16: Spread sobre CDI do CDB cativo | C16: 0 | D16: CDB rende 100% do CDI (informado)
B17: Custos cartoriais e fees fixos | C17: 1500 | D17: Estimativa de mercado
B19: CÁLCULO DOS JUROS (BULLET ÚNICO)
B20: Juros nominais (saldo × taxa × prazo / 360) | E20: =C7*C9*C8/C10 -> 29395
B22: COMPOSIÇÃO DO CUSTO EFETIVO TOTAL (R$)
B23: Juros nominais | E23: =E20 -> 29395 | F23: =E23/C7 -> 0.029395
B24: IRRF gross-up sobre juros (15%) | E24: =E20*C12/(1-C12) -> 5187.3529 | F24: =E24/C7 -> 0.0051873529
B25: IOF câmbio (0,38% entrada + saída) | E25: =C7*C13+(C7+E20+E20*C12/(1-C12))*C13 -> 7731.4129 | F25: =E25/C7 -> 0.0077314129
B26: Custo de oportunidade CDB cativo (30%) | E26: =C7*C14*(C15+C16)*C8/C10 -> 22125 | F26: =E26/C7 -> 0.022125
B27: Custos cartoriais e fees | E27: =C17 -> 1500 | F27: =E27/C7 -> 0.0015
B28: CUSTO EFETIVO TOTAL (R$) | E28: =SUM(E23:E27) -> 65938.766 | F28: =E28/C7 -> 0.065938766
B29: Custo total como % do principal | E29: =E28/C7 -> 0.065938766
B30: CET equivalente a.a. (anualizado composto) | E30: =(1+E29)^(C10/C8)-1 -> 0.13622545
B31: Custo equivalente linear a.a. | E31: =E29*C10/C8 -> 0.13187753

Sheet Cálculo Itaú
B2: CÁLCULO DETALHADO - FINIMP ITAÚ NASSAU (180 dias, sem spread cambial)
B3: Itaú usa estrutura híbrida com NDF (parte do custo cambial é alocado no derivativo). Spread cambial removido. Análise apresenta apenas o FINIMP "puro" - usar como referência.
B6: PREMISSAS DA OPERAÇÃO
B7: Valor da operação (R$) | C7: 1000000 | D7: Operação base
B8: Prazo (dias) | C8: 180 | D8: Cenário ajustado: 180 dias
B9: Taxa de juros nominal a.a. | C9: 0.048904 | D9: Quadro V - Taxa fixa de 4,890400% a.a.
B10: Base de cálculo (dias/ano) | C10: 360 | D10: Cláusula Encargos §1º
B11: Estrutura | C11: Bullet único | D11: Quadro VIII
B12: IRRF sobre juros remetidos a Nassau | C12: 0.25 | D12: Quadro V - 25% Nassau
B13: Comissão SBLC a.a. | C13: 0.007749 | D13: Quadro XIV - 0,7749% a.a.
B14: IOF câmbio (cada remessa) | C14: 0.0038 | D14: Alíquota geral 0,38%
B15: Cash Collateral (CDB cativo) - % do principal | C15: 0.3 | D15: Cessão fiduciária CDB
B16: Taxa CDI (custo de oportunidade) | C16: 0.1475 | D16: Premissa
B17: Spread sobre CDI do CDB cativo | C17: 0 | D17: CDB rende 100% do CDI (informado)
B18: Tarifa de contratação (estimada) | C18: 1500 | D18: Cláusula 11
B20: CÁLCULO DOS JUROS E COMISSÕES (BULLET ÚNICO)
B21: Juros nominais | E21: =C7*C9*C8/C10 -> 24452
B22: Comissão SBLC | E22: =C7*C13*C8/C10 -> 3874.5
B24: COMPOSIÇÃO DO CUSTO EFETIVO TOTAL (R$)
B25: Juros nominais | E25: =E21 -> 24452 | F25: =E25/C7 -> 0.024452
B26: IRRF gross-up sobre juros (25%) | E26: =E21*C12/(1-C12) -> 8150.6667 | F26: =E26/C7 -> 0.0081506667
B27: Comissão SBLC | E27: =E22 -> 3874.5 | F27: =E27/C7 -> 0.0038745
B28: IOF câmbio (0,38% entrada + saída) | E28: =C7*C14+(C7+E21+E21*C12/(1-C12)+E22)*C14 -> 7738.6132 | F28: =E28/C7 -> 0.0077386132
B29: Custo de oportunidade CDB cativo (30%) | E29: =C7*C15*(C16+C17)*C8/C10 -> 22125 | F29: =E29/C7 -> 0.022125
B30: Tarifa de contratação | E30: =C18 -> 1500 | F30: =E30/C7 -> 0.0015
B31: CUSTO EFETIVO TOTAL (R$) | E31: =SUM(E25:E30) -> 67840.78 | F31: =E31/C7 -> 0.06784078
B32: Custo total como % do principal | E32: =E31/C7 -> 0.06784078
B33: CET equivalente a.a. (composto) | E33: =(1+E32)^(C10/C8)-1 -> 0.14028393
B34: Custo equivalente linear a.a. | E34: =E32*C10/C8 -> 0.13568156

Sheet Cálculo Santander
B2: CÁLCULO DETALHADO - FINIMP SANTANDER LUXEMBURGO (180 dias, sem spread cambial)
B3: Cotação real Santander para FINIMP Direto USD. Taxa All-In 8,50% a.a. = 6,08% juros + 2,03% IR + 0,40% CPG. Spread cambial REMOVIDO (depende da oscilação do dólar no momento da operação).
B6: PREMISSAS DA OPERAÇÃO
B7: Valor da operação (R$) | C7: 1000000 | D7: Operação base
B8: Prazo (dias) | C8: 180 | D8: Cenário
B9: Taxa de juros nominal a.a. | C9: 0.0608 | D9: Cotação Santander - 6,08% a.a.
B10: Base de cálculo (dias/ano) | C10: 360 | D10: Padrão de mercado
B11: Estrutura | C11: Bullet único | D11: Cronograma da cotação
B12: IRRF sobre juros remetidos a Luxemburgo | C12: 0.25 | D12: Cotação - 2,03% / 6,08% × prazo = 25% gross-up
B13: CPG (Comissão de Permanência de Garantia) a.a. | C13: 0.004 | D13: Cotação - 0,40% a.a.
B14: IOF câmbio (cada remessa) | C14: 0.0038 | D14: Alíquota geral
B15: Cash Collateral (CDB cativo) - % do principal | C15: 0.3 | D15: Premissa: 30% (alinhado com BB e Itaú)
B16: Taxa CDI (custo de oportunidade) | C16: 0.1475 | D16: Premissa - SELIC/CDI atual
B17: Spread sobre CDI do CDB cativo | C17: 0 | D17: CDB rende 100% do CDI (informado)
B18: Tarifa ROF + CADEMP | C18: 2500 | D18: Cotação - R$ 2.000 + R$ 500
B20: CÁLCULO DOS JUROS E COMISSÕES (BULLET ÚNICO)
B21: Juros nominais | E21: =C7*C9*C8/C10 -> 30400
B22: CPG | E22: =C7*C13*C8/C10 -> 2000
B24: COMPOSIÇÃO DO CUSTO EFETIVO TOTAL (R$)
B25: Juros nominais (6,08% a.a.) | E25: =E21 -> 30400 | F25: =E25/C7 -> 0.0304
B26: IRRF gross-up sobre juros (25%) | E26: =E21*C12/(1-C12) -> 10133.333 | F26: =E26/C7 -> 0.010133333
B27: CPG (Comissão de Permanência de Garantia) | E27: =E22 -> 2000 | F27: =E27/C7 -> 0.002
B28: IOF câmbio (0,38% entrada + saída) | E28: =C7*C14+(C7+E21+E21*C12/(1-C12))*C14 -> 7754.0267 | F28: =E28/C7 -> 0.0077540267
B29: Custo de oportunidade CDB cativo (30%) | E29: =C7*C15*(C16+C17)*C8/C10 -> 22125 | F29: =E29/C7 -> 0.022125
B30: Tarifa ROF + CADEMP | E30: =C18 -> 2500 | F30: =E30/C7 -> 0.0025
B31: CUSTO EFETIVO TOTAL (R$) | E31: =SUM(E25:E30) -> 74912.36 | F31: =E31/C7 -> 0.07491236
B32: Custo total como % do principal | E32: =E31/C7 -> 0.07491236
B33: CET equivalente a.a. (composto) | E33: =(1+E32)^(C10/C8)-1 -> 0.15543658
B34: Custo equivalente linear a.a. | E34: =E32*C10/C8 -> 0.14982472

Sheet Entendendo o CET
B2: POR QUE O CET ANUALIZADO PARECE ALTO?
B3: A diferença entre "custo no semestre" e "CET anualizado" vem da matemática da capitalização composta. Esta aba decompõe e explica.
B6: 1. DECOMPOSIÇÃO DOS COMPONENTES (BB Tóquio - 180 dias)
B7: Componente | C7: Custo no semestre (R$) | D7: % Principal (180d) | E7: Linear a.a. | F7: Composto a.a. | G7: Por que
B8: Juros nominais (5,879% × 180/360) | C8: 29395 | D8: =C8/1000000 -> 0.029395 | E8: =D8*360/180 -> 0.05879 | F8: =(1+D8)^(360/180)-1 -> 0.059654066
B9: IRRF gross-up sobre juros (15%) | C9: 5187.35 | D9: =C9/1000000 -> 0.00518735 | E9: =D9*360/180 -> 0.0103747 | F9: =(1+D9)^(360/180)-1 -> 0.010401609
B10: IOF câmbio (0,38% sobre 2 conversões) | C10: 7731.41 | D10: =C10/1000000 -> 0.00773141 | E10: =D10*360/180 -> 0.01546282 | F10: =(1+D10)^(360/180)-1 -> 0.015522595
B11: CDB cativo 30% × (CDI 10,75% - 0,5%) × 180/360 | C11: 15375 | D11: =C11/1000000 -> 0.015375 | E11: =D11*360/180 -> 0.03075 | F11: =(1+D11)^(360/180)-1 -> 0.030986391
B12: Custos cartoriais e fees fixos | C12: 1500 | D12: =C12/1000000 -> 0.0015 | E12: =D12*360/180 -> 0.003 | F12: =(1+D12)^(360/180)-1 -> 0.00300225
B13: TOTAL | C13: =SUM(C8:C12) -> 59188.76 | D13: =C13/1000000 -> 0.05918876 | E13: =D13*360/180 -> 0.11837752 | F13: =(1+D13)^(360/180)-1 -> 0.12188083
B16: 2. POR QUE O CET COMPOSTO É MAIOR QUE O LINEAR?
B17: Imagine que o custo no semestre é 5,92% (BB sem spread cambial). Para anualizar, há duas formas:
B19: LINEAR (taxa proporcional): 5,92% × (360/180) = 11,84% a.a.
B20: COMPOSTO (juros sobre juros): (1 + 5,92%)^(360/180) - 1 = 12,19% a.a.
B22: O composto assume que se você fizesse a operação 2 vezes seguidas (semestre + semestre), os juros do segundo semestre incidiriam sobre o saldo após pagamento do primeiro - como uma renovação. A diferença pequena (0,35 p.p.) é o "juros sobre juros".
B24: Para FINIMP de prazo fixo (sem renovação automática), o CUSTO LINEAR é a métrica mais honesta - representa o custo proporcional anualizado.
B26: 3. POR QUE O 5,92% NO SEMESTRE PARECE ALTO?
B28: Olhe a coluna "% Principal (180d)" da tabela acima. Cada componente sozinho é pequeno, mas SOMADO chega a 5,92%:
B29: - Juros: 2,94% (= 5,879%/2)
B30: - IRRF: 0,52% (gross-up dos juros)
B31: - IOF: 0,77% (entrada + saída)
B32: - CDB cativo: 1,54% (oportunidade de R$ 300k bloqueados)
... B43: Use o "Custo equivalente LINEAR a.a." para comparar com outros instrumentos (CDI, SELIC, capital próprio). É mais intuitivo e justo para operações com prazo definido. O "CET composto" é mais útil para comparar com investimentos que efetivamente capitalizam (CDB, LFT, fundos).
